email_verification/__init__.py
email_verification/bulk_verifier.py
email_verification/email_validate.py
email_verifier_py4-0.1.2.dist-info/METADATA
email_verifier_py4-0.1.2.dist-info/WHEEL
email_verifier_py4-0.1.2.dist-info/top_level.txt
email_verifier_py4-0.1.2.dist-info/RECORD
